Metadata-Version: 2.4
Name: mseep-mcp-client
Version: 0.1.4
Summary: Add your description here
Author-email: mseep <support@skydeck.ai>
Requires-Python: >=3.11
Requires-Dist: mcp>=1.6.0
Requires-Dist: openai>=1.70.0
Requires-Dist: python-dotenv>=1.1.0
Requires-Dist: httpx>=0.28.1
